winslow/__init__.py
winslow/py.typed
winslow-0.1.0.dist-info/METADATA
winslow-0.1.0.dist-info/WHEEL
winslow-0.1.0.dist-info/RECORD
