Metadata-Version: 2.3
Name: winslow
Version: 0.1.0
Summary: Add your description here
Author-email: ocanbascil@gmail.com
Requires-Python: >=3.10
Requires-Dist: networkx>=3.4.2
Requires-Dist: textual>=0.85.2
